{
  "id": "Module3/Lectures/video7",
  "title": "The Event Function Blocks in IEC 61499",
  "description": "",
  "source": "@site/docs/Module3/Lectures/video7.md",
  "sourceDirName": "Module3/Lectures",
  "slug": "/Module3/Lectures/video7",
  "permalink": "/IEC61499-Curriculum/docs/Module3/Lectures/video7",
  "draft": false,
  "unlisted": false,
  "editUrl": "https://github.com/AIC3Lab/IEC61499-Curriculum/docs/Module3/Lectures/video7.md",
  "tags": [],
  "version": "current",
  "sidebarPosition": 9,
  "frontMatter": {
    "sidebar_position": 9
  },
  "sidebar": "tutorialSidebar",
  "previous": {
    "title": "The Composite Automation Type (CAT) in IEC 61499",
    "permalink": "/IEC61499-Curriculum/docs/Module3/Lectures/video6"
  },
  "next": {
    "title": "Lab",
    "permalink": "/IEC61499-Curriculum/docs/category/lab"
  }
}